avalon/__init__.py
avalon/for_humans.py
avalon/install_godot_binary.py
avalon/py.typed
avalon/agent/__init__.py
avalon/agent/train_dreamer_atari.py
avalon/agent/train_dreamer_avalon.py
avalon/agent/train_dreamer_dmc.py
avalon/agent/train_dreamer_test_envs.py
avalon/agent/train_ppo_avalon.py
avalon/agent/train_ppo_procgen.py
avalon/agent/train_ppo_test_envs.py
avalon/agent/common/__init__.py
avalon/agent/common/action_model.py
avalon/agent/common/dataloader.py
avalon/agent/common/envs.py
avalon/agent/common/get_algorithm_cls.py
avalon/agent/common/models.py
avalon/agent/common/params.py
avalon/agent/common/parse_args.py
avalon/agent/common/storage.py
avalon/agent/common/trainer.py
avalon/agent/common/types.py
avalon/agent/common/util.py
avalon/agent/common/wandb_lib.py
avalon/agent/common/worker.py
avalon/agent/common/wrappers.py
avalon/agent/dreamer/__init__.py
avalon/agent/dreamer/dreamer.py
avalon/agent/dreamer/models.py
avalon/agent/dreamer/params.py
avalon/agent/dreamer/readme_external.md
avalon/agent/dreamer/tools.py
avalon/agent/dreamer/truncated_normal.py
avalon/agent/godot/__init__.py
avalon/agent/godot/godot_eval.py
avalon/agent/godot/godot_gym.py
avalon/agent/ppo/__init__.py
avalon/agent/ppo/gae.py
avalon/agent/ppo/model.py
avalon/agent/ppo/observation_model.py
avalon/agent/ppo/params.py
avalon/agent/ppo/ppo.py
avalon/agent/ppo/ppo_types.py
avalon/agent/ppo/readme_external.md
avalon/agent/random_eval/__init__.py
avalon/agent/random_eval/evaluation.py
avalon/agent/tests/__init__.py
avalon/agent/tests/fixtures.py
avalon/agent/tests/generate_test_data.py
avalon/agent/tests/readme.md
avalon/agent/tests/simple_worker.py
avalon/agent/tests/utils.py
avalon/agent/tests/data/avalon_initial_observation.pkl
avalon/agent/tests/data/avalon_random_observation.pkl
avalon/agent/tests/data/dreamer_avalon_initial_forward_pass.pkl
avalon/agent/tests/data/dreamer_avalon_random_forward_pass.pkl
avalon/agent/tests/data/dreamer_avalon_trained_model_hash.pkl
avalon_rl-1.0.2.dist-info/LICENSE
avalon_rl-1.0.2.dist-info/LICENSE.md
avalon_rl-1.0.2.dist-info/METADATA
avalon_rl-1.0.2.dist-info/WHEEL
avalon_rl-1.0.2.dist-info/top_level.txt
avalon_rl-1.0.2.dist-info/RECORD
