Metadata-Version: 2.1
Name: avalon-rl
Version: 1.0.2
Summary: Avalon: A Benchmark for RL Generalization Using Procedurally Generated Worlds
Author-email: Generally Intelligent <avalon@generallyintelligent.com>
License: GNU GENERAL PUBLIC LICENSE
Requires-Python: >=3.9
License-File: LICENSE
License-File: LICENSE.md
Requires-Dist: attrs (>=21.4.0)
Requires-Dist: boto3 (>=1.20.47)
Requires-Dist: einops (>=0.3.2)
Requires-Dist: godot-parser (>=0.1.6)
Requires-Dist: gym (==0.25.2)
Requires-Dist: IPython (>=8.5.0)
Requires-Dist: loguru (>=0.6.0)
Requires-Dist: matplotlib (>=3.5.1)
Requires-Dist: moviepy (>=1.0.3)
Requires-Dist: networkx (>=2.6.3)
Requires-Dist: nptyping (>=2.0.1)
Requires-Dist: numpy (>=1.22.2)
Requires-Dist: openturns (>=1.19)
Requires-Dist: Pillow (>=9.0.1)
Requires-Dist: psutil (>=5.9.0)
Requires-Dist: requests (>=2.27.1)
Requires-Dist: rliable (>=1.0.7)
Requires-Dist: scipy (!=1.10.0,>=1.9.2)
Requires-Dist: sentry-sdk (>=1.5.4)
Requires-Dist: scikit-image (>=0.19.3)
Requires-Dist: sh (>=1.14.2)
Requires-Dist: shapely (>=1.7.0)
Requires-Dist: tqdm (>=4.62.3)
Requires-Dist: trimesh[easy] (>=3.15.5)
Requires-Dist: wandb (>=0.12.21)
Requires-Dist: imageio (>=2.15.0)
Requires-Dist: fire (>=0.4.0)
Provides-Extra: dev
Requires-Dist: deepdiff (>=5.8.1) ; extra == 'dev'
Requires-Dist: jupyter-ascending (>=0.1.23) ; extra == 'dev'
Requires-Dist: mypy (>=0.971) ; extra == 'dev'
Requires-Dist: notebook (>=6.4.8) ; extra == 'dev'
Requires-Dist: pytest (>=6.2.5) ; extra == 'dev'
Requires-Dist: pytest-forked (>=1.4.0) ; extra == 'dev'
Requires-Dist: pytest-integration (>=0.2.2) ; extra == 'dev'
Requires-Dist: pytest-xdist (>=2.5.0) ; extra == 'dev'
Requires-Dist: seaborn (>=0.11.2) ; extra == 'dev'
Requires-Dist: tabulate (>=0.8.9) ; extra == 'dev'
Requires-Dist: types-futures (>=3.3.8) ; extra == 'dev'
Requires-Dist: types-protobuf (>=3.19.4) ; extra == 'dev'
Requires-Dist: types-requests (>=2.27.1) ; extra == 'dev'
Requires-Dist: types-setuptools (>=57.4.9) ; extra == 'dev'
Requires-Dist: types-six (>=1.16.0) ; extra == 'dev'
Requires-Dist: types-tabulate (>=0.8.5) ; extra == 'dev'
Requires-Dist: types-toml (>=0.10.2) ; extra == 'dev'
Requires-Dist: types-urllib3 (>=1.26.9) ; extra == 'dev'
Requires-Dist: typing-extensions (>=4.1.1) ; extra == 'dev'
Requires-Dist: torch (>=1.12.0) ; extra == 'dev'
Provides-Extra: train
Requires-Dist: dm-tree (>=0.1.7) ; extra == 'train'
Requires-Dist: torch (>=1.12.0) ; extra == 'train'
Requires-Dist: torchvision (>=0.13.0) ; extra == 'train'
Requires-Dist: numba (>=0.56.4) ; extra == 'train'
